README.txt
setup.py
docs/HISTORY.txt
docs/INSTALL.txt
docs/LICENSE.GPL
docs/LICENSE.txt
medialog/__init__.py
medialog.foldersubskins.egg-info/PKG-INFO
medialog.foldersubskins.egg-info/SOURCES.txt
medialog.foldersubskins.egg-info/dependency_links.txt
medialog.foldersubskins.egg-info/entry_points.txt
medialog.foldersubskins.egg-info/namespace_packages.txt
medialog.foldersubskins.egg-info/not-zip-safe
medialog.foldersubskins.egg-info/requires.txt
medialog.foldersubskins.egg-info/top_level.txt
medialog/foldersubskins/__init__.py
medialog/foldersubskins/configure.zcml
medialog/foldersubskins/interfaces.py
medialog/foldersubskins/profiles.zcml
medialog/foldersubskins/schemaextender.py
medialog/foldersubskins/profiles/default/browserlayer.xml
medialog/foldersubskins/profiles/default/metadata.xml
medialog/foldersubskins/profiles/default/properties.xml
medialog/foldersubskins/profiles/default/viewlets.xml
medialog/foldersubskins/profiles/default/structure/.objects
medialog/foldersubskins/profiles/default/structure/.properties
medialog/foldersubskins/profiles/default/structure/layout01/.objects
medialog/foldersubskins/profiles/default/structure/layout01/.properties