Metadata-Version: 1.0
Name: medialog.foldersubskins
Version: 0.3.5
Summary: Makes it possible to have different layout on different parts of a plone site.
Home-page: http://medialog.no
Author: Grieg Medialog [Espen Moe-Nilssen]
Author-email: espen@medialog.no
License: GPL
Keywords: plone zope subskins sector custom css
Platform: UNKNOWN
Classifier: Framework :: Plone
Classifier: Programming Language :: Python
Classifier: Topic :: Software Development :: Libraries :: Python Modules
